Metadata-Version: 1.0
Name: pst-distributions
Version: 1.0
Summary: Gaussian and Binomial distributions
Home-page: UNKNOWN
Author: Olaoluwayemi Rasheed
Author-email: rasholayemi@gmail.com
License: UNKNOWN
Platform: UNKNOWN
